tfadm/__init__.py
tfadm/__main__.py
tfadm/exceptions.py
tfadm/module.py
tfadm/path.py
tfadm/properties.py
tfadm/resources.py
tfadm/settings.py
tfadm/template.py
tfadm/methods/__init__.py
tfadm/methods/sync.py
tfadm/methods/update.py
tfadm/methods/terraform/__init__.py
tfadm/methods/terraform/import_.py
tfadm/methods/terraform/init.py
tfadm/methods/terraform/show.py
tfadm-0.14.1.dist-info/METADATA
tfadm-0.14.1.dist-info/WHEEL
tfadm-0.14.1.dist-info/entry_points.txt
tfadm-0.14.1.dist-info/licenses/LICENSE
tfadm-0.14.1.dist-info/RECORD
