Metadata-Version: 2.1
Name: tfadm
Version: 0.14.1
Summary: Generates and modifies terraform code in JSON syntax.
Project-URL: Homepage, https://github.com/nuncard/tfadm
Project-URL: Bug Tracker, https://github.com/nuncard/tfadm/issues
Author: Nuno Cardoso
License: MIT License
License-File: LICENSE
Classifier: Development Status :: 4 - Beta
Classifier: Environment :: Console
Classifier: Intended Audience :: System Administrators
Classifier: License :: OSI Approved :: MIT License
Classifier: Operating System :: OS Independent
Classifier: Programming Language :: Python :: 3
Classifier: Topic :: System :: Systems Administration
Requires-Python: >=3.7
Requires-Dist: click>=8.0
Requires-Dist: jinja2>=3.0.0
Requires-Dist: parse>=1.19.0
Requires-Dist: python-slugify>=7.0.0
Requires-Dist: pyyaml>=6.0
